selectinf-0.1.3.dist-info/WHEEL
selectinf-0.1.3.dist-info/top_level.txt
selectinf-0.1.3.dist-info/METADATA
selectinf-0.1.3.dist-info/RECORD
selectinf/info.py
selectinf/api.py
selectinf/__init__.py
selectinf/_version.py
selectinf/base.py
selectinf/glm.py
selectinf/learning/samplers.py
selectinf/learning/Rfitters.py
selectinf/learning/learners.py
selectinf/learning/__init__.py
selectinf/learning/Rutils.py
selectinf/learning/core.py
selectinf/learning/utils.py
selectinf/learning/fitters.py
selectinf/learning/keras_fit.py
selectinf/truncated/gaussian.py
selectinf/truncated/T.py
selectinf/truncated/chi.py
selectinf/truncated/api.py
selectinf/truncated/__init__.py
selectinf/truncated/F.py
selectinf/truncated/base.py
selectinf/truncated/tests/__init__.py
selectinf/truncated/tests/test_truncatedFT.py
selectinf/truncated/tests/test_truncated.py
selectinf/constraints/intervals.py
selectinf/constraints/affine.py
selectinf/constraints/estimation.py
selectinf/constraints/api.py
selectinf/constraints/quasi_affine.py
selectinf/constraints/__init__.py
selectinf/constraints/quadratic.py
selectinf/constraints/base.py
selectinf/constraints/tests/test_estimation.py
selectinf/constraints/tests/test_quadratic_tests.py
selectinf/constraints/tests/__init__.py
selectinf/constraints/tests/test_quasi.py
selectinf/constraints/tests/test_unknown_sigma.py
selectinf/constraints/tests/test_affine.py
selectinf/sampling/truncnorm.cpython-37m-i386-linux-gnu.so
selectinf/sampling/sequential.py
selectinf/sampling/sqrt_lasso.cpython-37m-i386-linux-gnu.so
selectinf/sampling/api.py
selectinf/sampling/truncnorm_quadratic.cpython-37m-i386-linux-gnu.so
selectinf/sampling/__init__.py
selectinf/sampling/langevin.py
selectinf/sampling/tests/test_sequential.py
selectinf/sampling/tests/test_pca_langevin.py
selectinf/sampling/tests/__init__.py
selectinf/sampling/tests/test_kfstep.py
selectinf/sampling/tests/test_fstep_langevin.py
selectinf/sampling/tests/test_sample_sphere.py
selectinf/sampling/tests/plots_fs.py
selectinf/randomized/query.py
selectinf/randomized/api.py
