Metadata-Version: 2.1
Name: selectinf
Version: 0.1.3
Summary: Testing a fixed value of lambda
Home-page: http://github.org/jonathan.taylor/selective-inference
Author: fixed_lambda developers
Author-email: 
Maintainer: Jonathan Taylor
Maintainer-email: 
License: BSD license
Platform: OS Independent
Classifier: Development Status :: 3 - Alpha
Classifier: Environment :: Console
Classifier: Intended Audience :: Science/Research
Classifier: License :: OSI Approved :: BSD License
Classifier: Operating System :: OS Independent
Classifier: Programming Language :: Python
Classifier: Topic :: Scientific/Engineering
Requires: numpy (>=1.7.1)
Requires: scipy (>=0.9)
Requires: mpmath (>=0.18)
Requires: pyinter
Provides: fixed_lambda
Provides-Extra: test
Provides-Extra: doc
Requires-Dist: Cython (>=0.21)
Requires-Dist: scipy (>=0.9)
Provides-Extra: doc
Requires-Dist: Sphinx (>=1.0); extra == 'doc'
Provides-Extra: test
Requires-Dist: nose (>=0.10.1); extra == 'test'
